README.rst
setup.py
Flask_WXApp.egg-info/PKG-INFO
Flask_WXApp.egg-info/SOURCES.txt
Flask_WXApp.egg-info/dependency_links.txt
Flask_WXApp.egg-info/requires.txt
Flask_WXApp.egg-info/top_level.txt
flask_wxapp/__init__.py