Metadata-Version: 1.0
Name: Flask-WXApp
Version: 0.1.3
Summary: Flask Extension for WeChat App.
Home-page: https://github.com/codeif/Flask-WXApp
Author: codeif
Author-email: me@codeif.com
License: MIT
Platform: UNKNOWN
